julia_project/__init__.py
julia_project/_julia_project.py
julia_project/calljulia.py
julia_project/environment.py
julia_project/julia_system_image.py
julia_project/juliacall.py
julia_project/lib.py
julia_project/pyjulia.py
julia_project/questions.py
julia_project/savejuliacall.py
julia_project/uselibjulia.py
julia_project/utils.jl
julia_project/utils.py
julia_project/examples/myjuliamod/MANIFEST.in
julia_project/examples/myjuliamod/README.md
julia_project/examples/myjuliamod/requirements-dev.txt
julia_project/examples/myjuliamod/requirements.txt
julia_project/examples/myjuliamod/setup.py
julia_project/examples/myjuliamod/myjuliamod/Project.toml
julia_project/examples/myjuliamod/myjuliamod/__init__.py
julia_project/examples/myjuliamod/myjuliamod/_julia_project.py
julia_project/examples/myjuliamod/myjuliamod/hellomod.py
julia_project/examples/myjuliamod/myjuliamod/sys_image/Project.toml
julia_project/examples/myjuliamod/myjuliamod/sys_image/compile_exercise_script.jl
julia_project/examples/myjuliamod/myjuliamod/sys_image/packages.jl
julia_project-0.1.27.dist-info/LICENSE.md
julia_project-0.1.27.dist-info/METADATA
julia_project-0.1.27.dist-info/WHEEL
julia_project-0.1.27.dist-info/top_level.txt
julia_project-0.1.27.dist-info/RECORD
