Metadata-Version: 2.1
Name: julia-project
Version: 0.1.27
Summary: Manage Julia dependency in a Python module
Author: John Lapeyre
License: MIT
Platform: UNKNOWN
Classifier: Framework :: Django
Classifier: License :: OSI Approved :: MIT License
Classifier: Programming Language :: Python :: 3
License-File: LICENSE.md
Requires-Dist: julia (>=0.2)
Requires-Dist: juliacall (>=0.6.1)
Requires-Dist: find-julia (>=0.2.7)
Requires-Dist: julia-project-basic (>=0.1.5)
